discord_user_bot/__init__.py
discord_users_bot-0.0.1.1.dist-info/METADATA
discord_users_bot-0.0.1.1.dist-info/WHEEL
discord_users_bot-0.0.1.1.dist-info/top_level.txt
discord_users_bot-0.0.1.1.dist-info/RECORD
